evolution_strategy/__init__.py
evolution_strategy/evolution_strategy.py
evolution_strategy-0.0.0.1.dist-info/METADATA
evolution_strategy-0.0.0.1.dist-info/WHEEL
evolution_strategy-0.0.0.1.dist-info/top_level.txt
evolution_strategy-0.0.0.1.dist-info/RECORD
