Metadata-Version: 2.1
Name: evolution-strategy
Version: 0.0.0.1
Summary: Evolution Strategy
Home-page: https://gitee.com/fubo_linux/spider
Author: fubo
Author-email: fb_linux@163.com
License: UNKNOWN
Platform: UNKNOWN
Classifier: Programming Language :: Python :: 3
Classifier: License :: OSI Approved :: MIT License
Classifier: Operating System :: OS Independent
Requires-Python: >=3.8
Requires-Dist: tqdm (==4.56.0)
Requires-Dist: pydantic (==1.7.3)
Requires-Dist: tensorboardX (==2.1)
